{"top50": [
{
    "frequency":1.815723767466716,
    "word":"harvard"
},
{
    "frequency":0.6354454618336627,
    "word":"university"
},
{
    "frequency":0.5722949039233127,
    "word":"apply"
},
{
    "frequency":0.5484916409602202,
    "word":"research"
},
{
    "frequency":0.5460227727095707,
    "word":"filter"
},
{
    "frequency":0.5311627156107851,
    "word":"school"
},
{
    "frequency":0.4791899938409467,
    "word":"new"
},
{
    "frequency":0.41316767836390206,
    "word":"library"
},
{
    "frequency":0.4026082304759252,
    "word":"students"
},
{
    "frequency":0.39784851483520445,
    "word":"health"
},
{
    "frequency":0.317022359373241,
    "word":"faculty"
},
{
    "frequency":0.3054322643977065,
    "word":"center"
},
{
    "frequency":0.2843836400140861,
    "word":"program"
},
{
    "frequency":0.2787994067033193,
    "word":"sciences"
},
{
    "frequency":0.25894071122987916,
    "word":"public"
},
{
    "frequency":0.25132329230093037,
    "word":"arts"
},
{
    "frequency":0.24886379356925878,
    "word":"professor"
},
{
    "frequency":0.24125574415928783,
    "word":"american"
},
{
    "frequency":0.23727369859372424,
    "word":"college"
},
{
    "frequency":0.23673963601198977,
    "word":"policy"
},
{
    "frequency":0.23583547743063243,
    "word":"cambridge"
},
{
    "frequency":0.23023718984139888,
    "word":"education"
},
{
    "frequency":0.22037577111726783,
    "word":"work"
},
{
    "frequency":0.21455729983205604,
    "word":"history"
},
{
    "frequency":0.21110931684822687,
    "word":"institute"
},
{
    "frequency":0.20982100798877984,
    "word":"information"
},
{
    "frequency":0.20803142986402065,
    "word":"law"
},
{
    "frequency":0.20349189791927813,
    "word":"read"
},
{
    "frequency":0.20046085852996087,
    "word":"design"
},
{
    "frequency":0.1956683495728179,
    "word":"community"
},
{
    "frequency":0.19408021610608134,
    "word":"graduate"
},
{
    "frequency":0.19394435808090327,
    "word":"news"
},
{
    "frequency":0.18647216669611036,
    "word":"student"
},
{
    "frequency":0.18320220457285932,
    "word":"studies"
},
{
    "frequency":0.18039603363900922,
    "word":"study"
},
{
    "frequency":0.17595956640302246,
    "word":"change"
},
{
    "frequency":0.17595488164353357,
    "word":"year"
},
{
    "frequency":0.17293789653268302,
    "word":"time"
},
{
    "frequency":0.1721508569385481,
    "word":"use"
},
{
    "frequency":0.17132633926850196,
    "word":"president"
},
{
    "frequency":0.17100309086376797,
    "word":"urban"
},
{
    "frequency":0.16937279456163137,
    "word":"science"
},
{
    "frequency":0.16859512448647423,
    "word":"radcliffe"
},
{
    "frequency":0.16604193056502461,
    "word":"world"
},
{
    "frequency":0.1649831749205336,
    "word":"page"
},
{
    "frequency":0.15987210231814547,
    "word":"available"
},
{
    "frequency":0.15815748034520868,
    "word":"energy"
},
{
    "frequency":0.15714557229560663,
    "word":"street"
},
{
    "frequency":0.15578230728433723,
    "word":"privacy"
},
{
    "frequency":0.15342118850193245,
    "word":"contact"
}
]}